LICENSE.txt
README.md
setup.cfg
setup.py
pyHik.egg-info/PKG-INFO
pyHik.egg-info/SOURCES.txt
pyHik.egg-info/dependency_links.txt
pyHik.egg-info/requires.txt
pyHik.egg-info/top_level.txt
pyhik/__init__.py
pyhik/constants.py
pyhik/hikvision.py
pyhik/isapi.py
pyhik/watchdog.py
test/test_hikvision.py
test/test_isapi.py