Metadata-Version: 2.4
Name: pyHik
Version: 0.4.1
Summary: Python API for Hikvision cameras and NVRs - event streaming, ISAPI access, and device control.
Home-page: https://github.com/mezz64/pyhik
Download-URL: https://github.com/mezz64/pyhik/tarball/0.4.1
Author: John Mihalic
Author-email: mezz64@users.noreply.github.com
License: MIT
Keywords: hik,hikvision,event stream,events,api wrapper,homeassistant,isapi,nvr,camera
Classifier: Development Status :: 4 - Beta
Classifier: Intended Audience :: Developers
Classifier: License :: OSI Approved :: MIT License
Classifier: Programming Language :: Python :: 3
Classifier: Programming Language :: Python :: 3.9
Classifier: Programming Language :: Python :: 3.10
Classifier: Programming Language :: Python :: 3.11
Classifier: Programming Language :: Python :: 3.12
Requires-Python: >=3.9
License-File: LICENSE.txt
Requires-Dist: requests>=2.20.0
Provides-Extra: isapi
Requires-Dist: xmltodict>=0.13.0; extra == "isapi"
Dynamic: author
Dynamic: author-email
Dynamic: classifier
Dynamic: download-url
Dynamic: home-page
Dynamic: keywords
Dynamic: license
Dynamic: license-file
Dynamic: provides-extra
Dynamic: requires-dist
Dynamic: requires-python
Dynamic: summary
